{
  "tables": [
    {
      "name": "products",
      "columns": [
        {
          "name": "id",
          "type": "INTEGER",
          "autoIncrement": true,
          "primaryKey": true
        },
        { "name": "price", "type": "INTEGER" },
        { "name": "GTIN", "type": "INTEGER", "unique": true },
        { "name": "isExist", "type": "BOOLEAN" },
        { "name": "created_at", "type": "TIMESTAMP" }
      ]
    },
    {
      "name": "productsClone",
      "columns": [
        {
          "name": "id",
          "type": "INTEGER",
          "autoIncrement": true,
          "primaryKey": true
        },
        { "name": "price", "type": "INTEGER" },
        { "name": "GTIN", "type": "INTEGER", "unique": true },
        { "name": "isExist", "type": "BOOLEAN" },
        { "name": "created_at", "type": "TIMESTAMP" }
      ]
    }
  ]
}
